xcomponent-0.11.0.dist-info/METADATA
xcomponent-0.11.0.dist-info/WHEEL
xcomponent-0.11.0.dist-info/entry_points.txt
xcomponent-0.11.0.dist-info/licenses/LICENSE
xcomponent.libs/libgcc_s-262c4f60.so.1
xcomponent/__init__.py
xcomponent/adapters/__init__.py
xcomponent/adapters/babel.py
xcomponent/py.typed
xcomponent/service/__init__.py
xcomponent/service/catalog.py
xcomponent/xcore.cpython-314-arm-linux-musleabihf.so
xcomponent/xcore.pyi
xcomponent-0.11.0.dist-info/RECORD
