Metadata-Version: 2.4
Name: xcomponent
Version: 0.11.0
Classifier: License :: OSI Approved :: MIT License
Classifier: Programming Language :: Python :: 3
Classifier: Programming Language :: Python :: 3.11
Classifier: Programming Language :: Python :: 3.12
Classifier: Programming Language :: Python :: 3.13
Classifier: Programming Language :: Rust
Classifier: Topic :: Internet :: WWW/HTTP :: Dynamic Content
Classifier: Topic :: Software Development :: Libraries :: Python Modules
Classifier: Topic :: Software Development :: User Interfaces
Classifier: Topic :: Text Processing :: Markup :: HTML
Classifier: Typing :: Typed
Requires-Dist: furo>=2024.5.6 ; extra == 'docs'
Requires-Dist: linkify-it-py>=2.0.3,<3 ; extra == 'docs'
Requires-Dist: myst-parser>=4.0.0,<5 ; extra == 'docs'
Requires-Dist: sphinx>=8.0.0,<9 ; extra == 'docs'
Requires-Dist: sphinx-autodoc2>=0.5.0,<1 ; extra == 'docs'
Provides-Extra: docs
License-File: LICENSE
Summary: An embeded component base template engine - inspired by JSX
Author-email: Guillaume Gauvrit <guillaume@gauvr.it>
License: MIT
Requires-Python: >=3.11
Project-URL: Homepage, https://mardiros.github.io/xcomponent
Project-URL: Documentation, https://mardiros.github.io/xcomponent
Project-URL: Repository, https://github.com/mardiros/xcomponent.git
Project-URL: Issues, https://github.com/mardiros/xcomponent/issues
Project-URL: Changelog, https://mardiros.github.io/xcomponent/user/changelog.html
